MANIFEST.in
README.md
libraries.txt
setup.py
cms_bootstrap_templates/__init__.py
cms_bootstrap_templates/cms_plugins.py
cms_bootstrap_templates/settings.py
cms_bootstrap_templates/urls.py
cms_bootstrap_templates/wsgi.py
cms_bootstrap_templates.egg-info/PKG-INFO
cms_bootstrap_templates.egg-info/SOURCES.txt
cms_bootstrap_templates.egg-info/dependency_links.txt
cms_bootstrap_templates.egg-info/not-zip-safe
cms_bootstrap_templates.egg-info/requires.txt
cms_bootstrap_templates.egg-info/top_level.txt
cms_bootstrap_templates/static/cms_bootstrap_templates/less/bootstrap.less
cms_bootstrap_templates/static/cms_bootstrap_templates/less/template_header_two_columns.less
cms_bootstrap_templates/static/cms_bootstrap_templates/less/template_header_two_columns_left.less
cms_bootstrap_templates/static/cms_bootstrap_templates/less/template_header_two_columns_right.less
cms_bootstrap_templates/static/cms_bootstrap_templates/less/template_one_column.less
cms_bootstrap_templates/static/cms_bootstrap_templates/less/template_three_columns.less
cms_bootstrap_templates/static/cms_bootstrap_templates/less/template_two_columns.less
cms_bootstrap_templates/templates/cms_bootstrap_templates/alert.html
cms_bootstrap_templates/templates/cms_bootstrap_templates/image.html
cms_bootstrap_templates/templates/cms_bootstrap_templates/jumbotron.html
cms_bootstrap_templates/templates/cms_bootstrap_templates/pageheader.html
cms_bootstrap_templates/templates/cms_bootstrap_templates/panel.html
cms_bootstrap_templates/templates/cms_bootstrap_templates/template_header_two_column.html
cms_bootstrap_templates/templates/cms_bootstrap_templates/template_header_two_column_left.html
cms_bootstrap_templates/templates/cms_bootstrap_templates/template_header_two_column_right.html
cms_bootstrap_templates/templates/cms_bootstrap_templates/template_one_column.html
cms_bootstrap_templates/templates/cms_bootstrap_templates/template_three_column.html
cms_bootstrap_templates/templates/cms_bootstrap_templates/template_two_column.html
cms_bootstrap_templates/templates/cms_bootstrap_templates/well.html