Metadata-Version: 1.0
Name: cms-bootstrap-templates
Version: 1.1.0
Summary: This package provides a variety of Django CMS templates designed using Twitter Bootstrap
Home-page: UNKNOWN
Author: Charles Hathaway
Author-email: chathaway@logrit.com
License: UNKNOWN
Platform: UNKNOWN
